zex/sdk/__init__.py
zex/sdk/client/__init__.py
zex/sdk/client/async_client.py
zex/sdk/client/client.py
zex/sdk/client/signing_visitor.py
zex/sdk/client/signing_visitor_dev.py
zex/sdk/client/signing_visitor_main.py
zex/sdk/data_types/__init__.py
zex/sdk/data_types/asset.py
zex/sdk/data_types/cancel_order_request.py
zex/sdk/data_types/order.py
zex/sdk/data_types/place_order_request.py
zex/sdk/data_types/place_order_result.py
zex/sdk/data_types/trade_info.py
zex/sdk/data_types/transfer.py
zex/sdk/data_types/withdraw.py
zex/sdk/data_types/withdraw_request.py
zex/sdk/websocket/__init__.py
zex/sdk/websocket/base_socket.py
zex/sdk/websocket/execution_report_socket.py
zex/sdk/websocket/socket_message.py
zex/sdk/websocket/zex_socket_manager.py
zex_sdk-0.5.0.dist-info/METADATA
zex_sdk-0.5.0.dist-info/WHEEL
zex_sdk-0.5.0.dist-info/RECORD
