Metadata-Version: 2.1
Name: zex-sdk
Version: 0.5.0
Summary: Python client for Zex exchange.
Author-Email: Zex dev team <tech@zex.finance>
License: CC BY-NC
Requires-Python: <3.12,>=3.11
Requires-Dist: coincurve<22,>=21.0.0
Requires-Dist: eth-hash<1,>=0.7.0
Requires-Dist: eth-typing>=5.2.1
Requires-Dist: httpx<1,>=0.28.0
Requires-Dist: numpy<2,>=1.20.0
Requires-Dist: pycryptodome<4,>=3.23.0
Requires-Dist: pydantic<3,>=2.10.6
Requires-Dist: pydantic-settings<3,>=2.1.0
Requires-Dist: websockets<16,>=15.0.1
Requires-Dist: websockets_proxy<1,>=0.1.3
